<?xml version="1.0" encoding="UTF-8" standalone="yes"?>
<boModel>
    <id>ca9f9742-c8a9-4762-bb04-d5ff06781288</id>
    <createUser>admin</createUser>
    <createTime>2017-09-08 11:46:09</createTime>
    <updateUser></updateUser>
    <updateTime>2017-09-21 14:34:51</updateTime>
    <signature>DgQSSyFmOqrf7WQa6WFesZuTOnzFe+zevZg0BYW55MuhMOtUylRD92QW2MZY8fzuOKtRgEid9O6enDCAisnaxOQRXqQDKCxpde3bqr6tFcrsGzRz/UwrKaVvLLGBwiqW</signature>
    <managed>false</managed>
    <title>任务查询视图</title>
    <name>VIEW_ACT_TASKVIEW</name>
    <collection>false</collection>
    <system>false</system>
    <deleted>false</deleted>
    <categoryName>报表查询</categoryName>
    <administrator>admin</administrator>
    <entityType>VIEW</entityType>
    <viewType>COMMON</viewType>
    <viewSql>select infor.*,dept.departmentname processdeptname,orguser.username processusername,null as NOTEID from VIEW_ACT_TASK_TEMP  infor,ORGDEPARTMENT dept ,ORGUSER orguser 
where infor.createuserdeptid = dept.id and orguser.userid = infor.createuser</viewSql>
    <boItems>
        <boItem>
            <id>85b21ccd-338d-4618-90dc-11ccb1ae5532</id>
            <name>PROCESSINSTID</name>
            <title>PROCESSINSTID</title>
            <columnType>TEXT</columnType>
            <length>36</length>
            <nullable>false</nullable>
            <defaultValue></defaultValue>
            <columnWidth>100</columnWidth>
            <componentId>AWSUI.Text</componentId>
            <componentSetting>{}</componentSetting>
            <display>true</display>
            <deleted>false</deleted>
            <modify>true</modify>
            <componentExtendCode></componentExtendCode>
            <persistenceType>ENTITY</persistenceType>
            <validateType></validateType>
            <validateRule></validateRule>
            <validateTip></validateTip>
            <validateErr>0</validateErr>
            <tooltip></tooltip>
            <copy>false</copy>
            <displayRule></displayRule>
            <calcFormula></calcFormula>
        </boItem>
        <boItem>
            <id>555b6711-0601-405f-9b71-c7bc74603e67</id>
            <name>ID</name>
            <title>ID</title>
            <columnType>TEXT</columnType>
            <length>36</length>
            <nullable>false</nullable>
            <defaultValue></defaultValue>
            <columnWidth>100</columnWidth>
            <componentId>AWSUI.Text</componentId>
            <componentSetting>{}</componentSetting>
            <display>true</display>
            <deleted>false</deleted>
            <modify>true</modify>
            <componentExtendCode></componentExtendCode>
            <persistenceType>ENTITY</persistenceType>
            <validateType></validateType>
            <validateRule></validateRule>
            <validateTip></validateTip>
            <validateErr>0</validateErr>
            <tooltip></tooltip>
            <copy>false</copy>
            <displayRule></displayRule>
            <calcFormula></calcFormula>
        </boItem>
        <boItem>
            <id>783be989-8a4e-42a8-8ed6-f4ac1c2872fd</id>
            <name>ACTIVITYDEFID</name>
            <title>ACTIVITYDEFID</title>
            <columnType>TEXT</columnType>
            <length>36</length>
            <nullable>false</nullable>
            <defaultValue></defaultValue>
            <columnWidth>100</columnWidth>
            <componentId>AWSUI.Text</componentId>
            <componentSetting>{}</componentSetting>
            <display>true</display>
            <deleted>false</deleted>
            <modify>true</modify>
            <componentExtendCode></componentExtendCode>
            <persistenceType>ENTITY</persistenceType>
            <validateType></validateType>
            <validateRule></validateRule>
            <validateTip></validateTip>
            <validateErr>0</validateErr>
            <tooltip></tooltip>
            <copy>false</copy>
            <displayRule></displayRule>
            <calcFormula></calcFormula>
        </boItem>
        <boItem>
            <id>dd10f182-406c-4275-b12a-2874b390cccd</id>
            <name>PROCESSDEFID</name>
            <title>PROCESSDEFID</title>
            <columnType>TEXT</columnType>
            <length>36</length>
            <nullable>false</nullable>
            <defaultValue></defaultValue>
            <columnWidth>100</columnWidth>
            <componentId>AWSUI.Text</componentId>
            <componentSetting>{}</componentSetting>
            <display>true</display>
            <deleted>false</deleted>
            <modify>true</modify>
            <componentExtendCode></componentExtendCode>
            <persistenceType>ENTITY</persistenceType>
            <validateType></validateType>
            <validateRule></validateRule>
            <validateTip></validateTip>
            <validateErr>0</validateErr>
            <tooltip></tooltip>
            <copy>false</copy>
            <displayRule></displayRule>
            <calcFormula></calcFormula>
        </boItem>
        <boItem>
            <id>b4de2fc6-58b8-47f4-b09d-d188f5c25fca</id>
            <name>STATE</name>
            <title>STATE</title>
            <columnType>TEXT</columnType>
            <length>2</length>
            <nullable>false</nullable>
            <defaultValue></defaultValue>
            <columnWidth>100</columnWidth>
            <componentId>AWSUI.Text</componentId>
            <componentSetting>{}</componentSetting>
            <display>true</display>
            <deleted>false</deleted>
            <modify>true</modify>
            <componentExtendCode></componentExtendCode>
            <persistenceType>ENTITY</persistenceType>
            <validateType></validateType>
            <validateRule></validateRule>
            <validateTip></validateTip>
            <validateErr>0</validateErr>
            <tooltip></tooltip>
            <copy>false</copy>
            <displayRule></displayRule>
            <calcFormula></calcFormula>
        </boItem>
        <boItem>
            <id>b07669b1-1be7-413b-99b6-db0bc450e476</id>
            <name>OWNER</name>
            <title>OWNER</title>
            <columnType>TEXT</columnType>
            <length>36</length>
            <nullable>false</nullable>
            <defaultValue></defaultValue>
            <columnWidth>100</columnWidth>
            <componentId>AWSUI.Text</componentId>
            <componentSetting>{}</componentSetting>
            <display>true</display>
            <deleted>false</deleted>
            <modify>true</modify>
            <componentExtendCode></componentExtendCode>
            <persistenceType>ENTITY</persistenceType>
            <validateType></validateType>
            <validateRule></validateRule>
            <validateTip></validateTip>
            <validateErr>0</validateErr>
            <tooltip></tooltip>
            <copy>false</copy>
            <displayRule></displayRule>
            <calcFormula></calcFormula>
        </boItem>
        <boItem>
            <id>47da3a67-e929-4f52-b12d-8f1b90af9515</id>
            <name>TARGET</name>
            <title>TARGET</title>
            <columnType>TEXT</columnType>
            <length>36</length>
            <nullable>false</nullable>
            <defaultValue></defaultValue>
            <columnWidth>100</columnWidth>
            <componentId>AWSUI.Text</componentId>
            <componentSetting>{}</componentSetting>
            <display>true</display>
            <deleted>false</deleted>
            <modify>true</modify>
            <componentExtendCode></componentExtendCode>
            <persistenceType>ENTITY</persistenceType>
            <validateType></validateType>
            <validateRule></validateRule>
            <validateTip></validateTip>
            <validateErr>0</validateErr>
            <tooltip></tooltip>
            <copy>false</copy>
            <displayRule></displayRule>
            <calcFormula></calcFormula>
        </boItem>
        <boItem>
            <id>0b080791-4a63-4dae-8159-e6dcca193f8f</id>
            <name>BEGINTIME</name>
            <title>BEGINTIME</title>
            <columnType>DATE</columnType>
            <length>19</length>
            <nullable>false</nullable>
            <defaultValue></defaultValue>
            <columnWidth>200</columnWidth>
            <componentId>AWSUI.Date</componentId>
            <componentSetting>{}</componentSetting>
            <display>true</display>
            <deleted>false</deleted>
            <modify>true</modify>
            <componentExtendCode></componentExtendCode>
            <persistenceType>ENTITY</persistenceType>
            <validateType></validateType>
            <validateRule></validateRule>
            <validateTip></validateTip>
            <validateErr>0</validateErr>
            <tooltip></tooltip>
            <copy>false</copy>
            <displayRule></displayRule>
            <calcFormula></calcFormula>
        </boItem>
        <boItem>
            <id>59dfa6e3-f2c0-47fc-b9e6-f69e8029a817</id>
            <name>OWNERDEPTID</name>
            <title>OWNERDEPTID</title>
            <columnType>TEXT</columnType>
            <length>36</length>
            <nullable>false</nullable>
            <defaultValue></defaultValue>
            <columnWidth>100</columnWidth>
            <componentId>AWSUI.Text</componentId>
            <componentSetting>{}</componentSetting>
            <display>true</display>
            <deleted>false</deleted>
            <modify>true</modify>
            <componentExtendCode></componentExtendCode>
            <persistenceType>ENTITY</persistenceType>
            <validateType></validateType>
            <validateRule></validateRule>
            <validateTip></validateTip>
            <validateErr>0</validateErr>
            <tooltip></tooltip>
            <copy>false</copy>
            <displayRule></displayRule>
            <calcFormula></calcFormula>
        </boItem>
        <boItem>
            <id>f6b9216f-ee42-4148-96af-f92e2ca80e68</id>
            <name>TARGETDEPTID</name>
            <title>TARGETDEPTID</title>
            <columnType>TEXT</columnType>
            <length>36</length>
            <nullable>false</nullable>
            <defaultValue></defaultValue>
            <columnWidth>100</columnWidth>
            <componentId>AWSUI.Text</componentId>
            <componentSetting>{}</componentSetting>
            <display>true</display>
            <deleted>false</deleted>
            <modify>true</modify>
            <componentExtendCode></componentExtendCode>
            <persistenceType>ENTITY</persistenceType>
            <validateType></validateType>
            <validateRule></validateRule>
            <validateTip></validateTip>
            <validateErr>0</validateErr>
            <tooltip></tooltip>
            <copy>false</copy>
            <displayRule></displayRule>
            <calcFormula></calcFormula>
        </boItem>
        <boItem>
            <id>79bdf05b-35e2-447f-8968-e3ba9679c167</id>
            <name>ENDTIME</name>
            <title>ENDTIME</title>
            <columnType>TEXT</columnType>
            <length>19</length>
            <nullable>false</nullable>
            <defaultValue></defaultValue>
            <columnWidth>100</columnWidth>
            <componentId>AWSUI.Text</componentId>
            <componentSetting>{}</componentSetting>
            <display>true</display>
            <deleted>false</deleted>
            <modify>true</modify>
            <componentExtendCode></componentExtendCode>
            <persistenceType>ENTITY</persistenceType>
            <validateType></validateType>
            <validateRule></validateRule>
            <validateTip></validateTip>
            <validateErr>0</validateErr>
            <tooltip></tooltip>
            <copy>false</copy>
            <displayRule></displayRule>
            <calcFormula></calcFormula>
        </boItem>
        <boItem>
            <id>bcb75cda-3195-4ef0-a2a8-2d74fc0d889b</id>
            <name>COSTTTIME</name>
            <title>COSTTTIME</title>
            <columnType>NUMBER</columnType>
            <length>12</length>
            <nullable>false</nullable>
            <defaultValue></defaultValue>
            <columnWidth>100</columnWidth>
            <componentId>AWSUI.Number</componentId>
            <componentSetting>{}</componentSetting>
            <display>true</display>
            <deleted>false</deleted>
            <modify>true</modify>
            <componentExtendCode></componentExtendCode>
            <persistenceType>ENTITY</persistenceType>
            <validateType></validateType>
            <validateRule></validateRule>
            <validateTip></validateTip>
            <validateErr>0</validateErr>
            <tooltip></tooltip>
            <copy>false</copy>
            <displayRule></displayRule>
            <calcFormula></calcFormula>
        </boItem>
        <boItem>
            <id>dfe6820d-5279-4faa-ac69-c88e700dfa67</id>
            <name>PROCESSAPP</name>
            <title>PROCESSAPP</title>
            <columnType>TEXT</columnType>
            <length>100</length>
            <nullable>false</nullable>
            <defaultValue></defaultValue>
            <columnWidth>100</columnWidth>
            <componentId>AWSUI.Text</componentId>
            <componentSetting>{}</componentSetting>
            <display>true</display>
            <deleted>false</deleted>
            <modify>true</modify>
            <componentExtendCode></componentExtendCode>
            <persistenceType>ENTITY</persistenceType>
            <validateType></validateType>
            <validateRule></validateRule>
            <validateTip></validateTip>
            <validateErr>0</validateErr>
            <tooltip></tooltip>
            <copy>false</copy>
            <displayRule></displayRule>
            <calcFormula></calcFormula>
        </boItem>
        <boItem>
            <id>eb5474a8-6497-451f-a29f-84f2e4752b02</id>
            <name>PROCESSNAME</name>
            <title>PROCESSNAME</title>
            <columnType>TEXT</columnType>
            <length>100</length>
            <nullable>false</nullable>
            <defaultValue></defaultValue>
            <columnWidth>100</columnWidth>
            <componentId>AWSUI.Text</componentId>
            <componentSetting>{}</componentSetting>
            <display>true</display>
            <deleted>false</deleted>
            <modify>true</modify>
            <componentExtendCode></componentExtendCode>
            <persistenceType>ENTITY</persistenceType>
            <validateType></validateType>
            <validateRule></validateRule>
            <validateTip></validateTip>
            <validateErr>0</validateErr>
            <tooltip></tooltip>
            <copy>false</copy>
            <displayRule></displayRule>
            <calcFormula></calcFormula>
        </boItem>
        <boItem>
            <id>3d441439-74f1-4e26-8311-06d18f06b9ee</id>
            <name>PROCESSTITLE</name>
            <title>PROCESSTITLE</title>
            <columnType>TEXT</columnType>
            <length>255</length>
            <nullable>false</nullable>
            <defaultValue></defaultValue>
            <columnWidth>100</columnWidth>
            <componentId>AWSUI.Text</componentId>
            <componentSetting>{}</componentSetting>
            <display>true</display>
            <deleted>false</deleted>
            <modify>true</modify>
            <componentExtendCode></componentExtendCode>
            <persistenceType>ENTITY</persistenceType>
            <validateType></validateType>
            <validateRule></validateRule>
            <validateTip></validateTip>
            <validateErr>0</validateErr>
            <tooltip></tooltip>
            <copy>false</copy>
            <displayRule></displayRule>
            <calcFormula></calcFormula>
        </boItem>
        <boItem>
            <id>ee843b31-6e16-4e99-9b21-1790b08b5871</id>
            <name>CREATEUSER</name>
            <title>CREATEUSER</title>
            <columnType>TEXT</columnType>
            <length>36</length>
            <nullable>false</nullable>
            <defaultValue></defaultValue>
            <columnWidth>100</columnWidth>
            <componentId>AWSUI.Text</componentId>
            <componentSetting>{}</componentSetting>
            <display>true</display>
            <deleted>false</deleted>
            <modify>true</modify>
            <componentExtendCode></componentExtendCode>
            <persistenceType>ENTITY</persistenceType>
            <validateType></validateType>
            <validateRule></validateRule>
            <validateTip></validateTip>
            <validateErr>0</validateErr>
            <tooltip></tooltip>
            <copy>false</copy>
            <displayRule></displayRule>
            <calcFormula></calcFormula>
        </boItem>
        <boItem>
            <id>5e819c87-ab59-479c-b41a-72432ced40b4</id>
            <name>CREATETIME</name>
            <title>CREATETIME</title>
            <columnType>DATE</columnType>
            <length>19</length>
            <nullable>false</nullable>
            <defaultValue></defaultValue>
            <columnWidth>200</columnWidth>
            <componentId>AWSUI.Date</componentId>
            <componentSetting>{}</componentSetting>
            <display>true</display>
            <deleted>false</deleted>
            <modify>true</modify>
            <componentExtendCode></componentExtendCode>
            <persistenceType>ENTITY</persistenceType>
            <validateType></validateType>
            <validateRule></validateRule>
            <validateTip></validateTip>
            <validateErr>0</validateErr>
            <tooltip></tooltip>
            <copy>false</copy>
            <displayRule></displayRule>
            <calcFormula></calcFormula>
        </boItem>
        <boItem>
            <id>cd4b04e4-eebd-4e2b-898b-e080f8664cb4</id>
            <name>CREATEUSERDEPTID</name>
            <title>CREATEUSERDEPTID</title>
            <columnType>TEXT</columnType>
            <length>36</length>
            <nullable>false</nullable>
            <defaultValue></defaultValue>
            <columnWidth>100</columnWidth>
            <componentId>AWSUI.Text</componentId>
            <componentSetting>{}</componentSetting>
            <display>true</display>
            <deleted>false</deleted>
            <modify>true</modify>
            <componentExtendCode></componentExtendCode>
            <persistenceType>ENTITY</persistenceType>
            <validateType></validateType>
            <validateRule></validateRule>
            <validateTip></validateTip>
            <validateErr>0</validateErr>
            <tooltip></tooltip>
            <copy>false</copy>
            <displayRule></displayRule>
            <calcFormula></calcFormula>
        </boItem>
        <boItem>
            <id>32ccc7cb-3415-48ce-8d16-f50341507c3e</id>
            <name>TASKUSERNAME</name>
            <title>TASKUSERNAME</title>
            <columnType>TEXT</columnType>
            <length>36</length>
            <nullable>false</nullable>
            <defaultValue></defaultValue>
            <columnWidth>100</columnWidth>
            <componentId>AWSUI.Text</componentId>
            <componentSetting>{}</componentSetting>
            <display>true</display>
            <deleted>false</deleted>
            <modify>true</modify>
            <componentExtendCode></componentExtendCode>
            <persistenceType>ENTITY</persistenceType>
            <validateType></validateType>
            <validateRule></validateRule>
            <validateTip></validateTip>
            <validateErr>0</validateErr>
            <tooltip></tooltip>
            <copy>false</copy>
            <displayRule></displayRule>
            <calcFormula></calcFormula>
        </boItem>
        <boItem>
            <id>3ffd6f01-593b-48eb-af02-a2c44ae83450</id>
            <name>TARGETDEPTNAME</name>
            <title>TARGETDEPTNAME</title>
            <columnType>TEXT</columnType>
            <length>128</length>
            <nullable>false</nullable>
            <defaultValue></defaultValue>
            <columnWidth>100</columnWidth>
            <componentId>AWSUI.Text</componentId>
            <componentSetting>{}</componentSetting>
            <display>true</display>
            <deleted>false</deleted>
            <modify>true</modify>
            <componentExtendCode></componentExtendCode>
            <persistenceType>ENTITY</persistenceType>
            <validateType></validateType>
            <validateRule></validateRule>
            <validateTip></validateTip>
            <validateErr>0</validateErr>
            <tooltip></tooltip>
            <copy>false</copy>
            <displayRule></displayRule>
            <calcFormula></calcFormula>
        </boItem>
        <boItem>
            <id>7e32374b-db4a-4d91-9316-6ed6fcd667eb</id>
            <name>processdeptname</name>
            <title>processdeptname</title>
            <columnType>TEXT</columnType>
            <length>128</length>
            <nullable>false</nullable>
            <defaultValue></defaultValue>
            <columnWidth>100</columnWidth>
            <componentId>AWSUI.Text</componentId>
            <componentSetting>{}</componentSetting>
            <display>true</display>
            <deleted>false</deleted>
            <modify>true</modify>
            <componentExtendCode></componentExtendCode>
            <persistenceType>ENTITY</persistenceType>
            <validateType></validateType>
            <validateRule></validateRule>
            <validateTip></validateTip>
            <validateErr>0</validateErr>
            <tooltip></tooltip>
            <copy>false</copy>
            <displayRule></displayRule>
            <calcFormula></calcFormula>
        </boItem>
        <boItem>
            <id>6a98bb34-d092-4e50-aef1-1fb58390c10e</id>
            <name>processusername</name>
            <title>processusername</title>
            <columnType>TEXT</columnType>
            <length>36</length>
            <nullable>false</nullable>
            <defaultValue></defaultValue>
            <columnWidth>100</columnWidth>
            <componentId>AWSUI.Text</componentId>
            <componentSetting>{}</componentSetting>
            <display>true</display>
            <deleted>false</deleted>
            <modify>true</modify>
            <componentExtendCode></componentExtendCode>
            <persistenceType>ENTITY</persistenceType>
            <validateType></validateType>
            <validateRule></validateRule>
            <validateTip></validateTip>
            <validateErr>0</validateErr>
            <tooltip></tooltip>
            <copy>false</copy>
            <displayRule></displayRule>
            <calcFormula></calcFormula>
        </boItem>
        <boItem>
            <id>e933655c-d56f-497a-afe7-f40dc53c6717</id>
            <name>NOTEID</name>
            <title>NOTEID</title>
            <columnType>TEXT</columnType>
            <length>0</length>
            <nullable>false</nullable>
            <defaultValue></defaultValue>
            <columnWidth>100</columnWidth>
            <componentId>AWSUI.Text</componentId>
            <componentSetting>{}</componentSetting>
            <display>true</display>
            <deleted>false</deleted>
            <modify>true</modify>
            <componentExtendCode></componentExtendCode>
            <persistenceType>ENTITY</persistenceType>
            <validateType></validateType>
            <validateRule></validateRule>
            <validateTip></validateTip>
            <validateErr>0</validateErr>
            <tooltip></tooltip>
            <copy>false</copy>
            <displayRule></displayRule>
            <calcFormula></calcFormula>
        </boItem>
    </boItems>
    <boIndexs/>
    <boRelations/>
</boModel>
